spb/__init__.py
spb/_version.py
spb/defaults.py
spb/plotgrid.py
spb/utils.py
spb/wegert.py
spb/animation/__init__.py
spb/animation/ipywidgets.py
spb/animation/panel.py
spb/backends/__init__.py
spb/backends/base_backend.py
spb/backends/base_renderer.py
spb/backends/utils.py
spb/backends/bokeh/__init__.py
spb/backends/bokeh/bokeh.py
spb/backends/bokeh/renderers/__init__.py
spb/backends/bokeh/renderers/arrow2d.py
spb/backends/bokeh/renderers/complex.py
spb/backends/bokeh/renderers/contour.py
spb/backends/bokeh/renderers/generic.py
spb/backends/bokeh/renderers/geometry.py
spb/backends/bokeh/renderers/hvline.py
spb/backends/bokeh/renderers/line2d.py
spb/backends/bokeh/renderers/mcircles.py
spb/backends/bokeh/renderers/ngrid.py
spb/backends/bokeh/renderers/nichols.py
spb/backends/bokeh/renderers/nyquist.py
spb/backends/bokeh/renderers/polezero.py
spb/backends/bokeh/renderers/root_locus.py
spb/backends/bokeh/renderers/sgrid.py
spb/backends/bokeh/renderers/vector2d.py
spb/backends/bokeh/renderers/zgrid.py
spb/backends/k3d/__init__.py
spb/backends/k3d/k3d.py
spb/backends/k3d/renderers/__init__.py
spb/backends/k3d/renderers/arrow3d.py
spb/backends/k3d/renderers/complex.py
spb/backends/k3d/renderers/geometry.py
spb/backends/k3d/renderers/implicit3d.py
spb/backends/k3d/renderers/line3d.py
spb/backends/k3d/renderers/surface.py
spb/backends/k3d/renderers/vector3d.py
spb/backends/matplotlib/__init__.py
spb/backends/matplotlib/matplotlib.py
spb/backends/matplotlib/renderers/__init__.py
spb/backends/matplotlib/renderers/_sgrid_helper.py
spb/backends/matplotlib/renderers/arrow2d.py
spb/backends/matplotlib/renderers/arrow3d.py
spb/backends/matplotlib/renderers/complex.py
spb/backends/matplotlib/renderers/contour.py
spb/backends/matplotlib/renderers/generic.py
spb/backends/matplotlib/renderers/geometry.py
spb/backends/matplotlib/renderers/hvline.py
spb/backends/matplotlib/renderers/implicit2d.py
spb/backends/matplotlib/renderers/line2d.py
spb/backends/matplotlib/renderers/line3d.py
sympy_plot_backends-4.1.0.dist-info/licenses/LICENSE
sympy_plot_backends-4.1.0.dist-info/METADATA
sympy_plot_backends-4.1.0.dist-info/WHEEL
sympy_plot_backends-4.1.0.dist-info/top_level.txt
sympy_plot_backends-4.1.0.dist-info/RECORD
