Metadata-Version: 2.4
Name: sympy_plot_backends
Version: 4.1.0
Summary: Backends for plotting with SymPy
Home-page: https://github.com/Davide-sd/sympy-plot-backends
Author: Davide Sandona
Author-email: sandona.davide@gmail.com
License: BSD License
Keywords: sympy plot plotting backend plotly bokeh mayavi k3d panel
Classifier: Development Status :: 5 - Production/Stable
Classifier: License :: OSI Approved :: BSD License
Classifier: Programming Language :: Python :: 3.9
Classifier: Topic :: Scientific/Engineering
Classifier: Topic :: Scientific/Engineering :: Mathematics
Classifier: Topic :: Scientific/Engineering :: Physics
License-File: LICENSE
Requires-Dist: packaging
Requires-Dist: appdirs>=1.4.4
Requires-Dist: param
Requires-Dist: numpy>=1.21.1
Requires-Dist: sympy>=1.10.1
Requires-Dist: matplotlib>3.4.2
Requires-Dist: mergedeep>=1.3.4
Provides-Extra: all
Requires-Dist: scipy>=1.7.1; extra == "all"
Requires-Dist: adaptive>=0.13.1; extra == "all"
Requires-Dist: notebook; extra == "all"
Requires-Dist: ipympl>=0.7.0; extra == "all"
Requires-Dist: plotly>=4.14.3; extra == "all"
Requires-Dist: panel>=1.0.0; extra == "all"
Requires-Dist: ipywidgets_bokeh; extra == "all"
Requires-Dist: colorcet; extra == "all"
Requires-Dist: k3d>=2.9.7; extra == "all"
Requires-Dist: vtk; extra == "all"
Requires-Dist: control>=0.10.0; extra == "all"
Requires-Dist: imageio; extra == "all"
Requires-Dist: imageio-ffmpeg; extra == "all"
Requires-Dist: psutil; extra == "all"
Requires-Dist: av; extra == "all"
Requires-Dist: tqdm; extra == "all"
Provides-Extra: dev
Requires-Dist: scipy>=1.7.1; extra == "dev"
Requires-Dist: adaptive>=0.13.1; extra == "dev"
Requires-Dist: notebook; extra == "dev"
Requires-Dist: ipympl>=0.7.0; extra == "dev"
Requires-Dist: plotly>=4.14.3; extra == "dev"
Requires-Dist: panel>=1.0.0; extra == "dev"
Requires-Dist: ipywidgets_bokeh; extra == "dev"
Requires-Dist: colorcet; extra == "dev"
Requires-Dist: k3d>=2.9.7; extra == "dev"
Requires-Dist: vtk; extra == "dev"
Requires-Dist: control>=0.10.0; extra == "dev"
Requires-Dist: imageio; extra == "dev"
Requires-Dist: imageio-ffmpeg; extra == "dev"
Requires-Dist: psutil; extra == "dev"
Requires-Dist: av; extra == "dev"
Requires-Dist: tqdm; extra == "dev"
Requires-Dist: pytest; extra == "dev"
Requires-Dist: pytest-mock; extra == "dev"
Requires-Dist: sphinx; extra == "dev"
Requires-Dist: sphinx-rtd-theme; extra == "dev"
Requires-Dist: kaleido; extra == "dev"
Requires-Dist: numpydoc; extra == "dev"
Dynamic: author
Dynamic: author-email
Dynamic: classifier
Dynamic: description
Dynamic: description-content-type
Dynamic: home-page
Dynamic: keywords
Dynamic: license
Dynamic: license-file
Dynamic: provides-extra
Dynamic: requires-dist
Dynamic: summary
